{"mode":"platformer_arcade","coordinates":"origin_top_left_x_right_y_down_pixels","screen":"playing","level":{"index":1,"total":5,"id":"iron-ascent-9","name":"Iron Ascent IX"},"campaign":{"route":["iron-ascent-9","crystal-spire-8","night-metro-6","molten-overseer-10","citadel-heart-12"],"bossLevels":2},"layout":"vertical","visualStyle":"fortress","isBossLevel":false,"boss":null,"score":220,"lives":2,"timeLeft":119.22,"coins":{"collected":0,"total":13},"player":{"x":714,"y":738.49,"vx":0,"vy":29.67,"onGround":false,"facing":"right","powerLevel":0,"animation":"jump"},"enemies":[{"id":"enemy-iron-ascent-9-0","type":"walker","x":312.87,"y":744.47,"vx":62,"direction":1},{"id":"enemy-iron-ascent-9-2","type":"walker","x":1016.8,"y":744.47,"vx":62,"direction":1},{"id":"enemy-iron-ascent-9-3","type":"walker","x":1124.13,"y":712,"vx":62,"direction":1},{"id":"enemy-iron-ascent-9-4","type":"walker","x":824.63,"y":328.47,"vx":-62,"direction":-1}],"items":[{"id":"item-iron-ascent-9-0","type":"coin","x":231,"y":583},{"id":"item-iron-ascent-9-1","type":"coin","x":263,"y":583},{"id":"item-iron-ascent-9-2","type":"coin","x":519,"y":487},{"id":"item-iron-ascent-9-3","type":"coin","x":551,"y":487},{"id":"item-iron-ascent-9-4","type":"coin","x":839,"y":423},{"id":"item-iron-ascent-9-5","type":"coin","x":871,"y":423},{"id":"item-iron-ascent-9-6","type":"coin","x":967,"y":359},{"id":"item-iron-ascent-9-7","type":"coin","x":999,"y":359},{"id":"item-iron-ascent-9-8","type":"coin","x":1191,"y":295},{"id":"item-iron-ascent-9-9","type":"coin","x":1223,"y":295},{"id":"item-iron-ascent-9-10","type":"coin","x":1063,"y":135},{"id":"item-iron-ascent-9-11","type":"coin","x":1095,"y":135},{"id":"item-iron-ascent-9-12","type":"coin","x":1127,"y":135}],"projectiles":[],"goal":{"x":1091,"y":-2},"camera":{"x":377,"y":400},"message":"Stomped enemy."}