{"mode":"adventure","coordinates":"origin_top_left_x_right_y_down","status":"playing","turn":8,"player":{"x":0,"y":7,"health":14,"stamina":24,"daylight":16,"hasRelic":false},"objectives":{"base":{"x":0,"y":7},"relicKnown":false,"relicDistanceHint":7,"extractionDistance":0},"resources":{"threat":0,"threatTier":"Baja","scanCharges":0,"scanTurns":0,"rations":0,"beacons":1,"beaconTurns":0,"jumps":0,"jumpTurns":0},"map":{"size":8,"visibleTiles":[{"x":0,"y":6,"terrain":"forest","visited":false},{"x":0,"y":7,"terrain":"ruins","visited":true},{"x":1,"y":7,"terrain":"dunes","visited":false}]},"message":"Usas una racion: recuperas energia y estabilizas la ruta."}