{"mode":"strategy-brisca-ai","variant":"brisca_duel","locale":"es","status":"playing","resolvingTrick":false,"turnTransitioning":false,"drawAnimating":false,"round":1,"trick":3,"current":"human","stockCount":29,"trumpSuit":"espadas","players":[{"id":"human","name":"Tu","side":"user","isHuman":true,"handCount":3,"points":0},{"id":"ai-1","name":"IA 1","side":"rival","isHuman":false,"handCount":2,"points":2}],"score":{"rounds":{"user":0,"rival":0},"sidePoints":{"user":0,"rival":2}},"tableCards":[{"playerId":"ai-1","card":"S♦"}],"hands":{"human":["2♣","R♠","6♣"]},"teammateHint":null,"actions":{"playableIndexes":[1,2,3],"canNextRound":false,"canRestart":true},"message":"Tu turno: juega carta."}